README.txt
setup.py
Products/__init__.py
Products.ColorField.egg-info/PKG-INFO
Products.ColorField.egg-info/SOURCES.txt
Products.ColorField.egg-info/dependency_links.txt
Products.ColorField.egg-info/entry_points.txt
Products.ColorField.egg-info/namespace_packages.txt
Products.ColorField.egg-info/not-zip-safe
Products.ColorField.egg-info/paster_plugins.txt
Products.ColorField.egg-info/requires.txt
Products.ColorField.egg-info/top_level.txt
Products/ColorField/__init__.py
Products/ColorField/_field.py
Products/ColorField/config.py
Products/ColorField/configure.zcml
Products/ColorField/skins.zcml
Products/ColorField/version.txt
Products/ColorField/profiles/default/metadata.xml
Products/ColorField/profiles/default/skins.xml
Products/ColorField/skins/ColorField/colorpicker.js
Products/ColorField/skins/ColorField/colorpicker.pt
Products/ColorField/skins/ColorField/colorpicker_popup.pt
Products/ColorField/skins/ColorField/marquee.gif
Products/ColorField/skins/ColorField/pixel.gif
Products/ColorField/tests/__init__.py
Products/ColorField/tests/base.py
Products/ColorField/tests/test_setup.py
docs/CREDITS.txt
docs/HISTORY.txt
docs/INSTALL.txt
docs/LICENSE.txt