Metadata-Version: 1.0
Name: Products.ColorField
Version: 0.3.1
Summary: ColorField is a color picker and converter for Plone Archetypes.
Home-page: http://pypi.python.org/pypi/Products.ColorField/
Author: Roland Fasching
Author-email: rof@sterngasse.at
License: GPL
Platform: UNKNOWN
Classifier: Framework :: Plone
Classifier: Programming Language :: Python
Classifier: Topic :: Software Development :: Libraries :: Python Modules
